{
	"parent": "block/block",
	"textures": {
		"particle": "the_garden:block/mulch",
		"main": "the_garden:block/mulch"
	},
	"elements": [
		{
			"from": [ 0, 0, 0 ],
			"to": [ 16, 16, 16 ],
			"faces": {
				"down": { "texture": "#main", "tintindex": 0, "cullface": "down" },
				"up": { "texture": "#main", "tintindex": 0 },
				"north": { "texture": "#main", "tintindex": 0, "cullface": "north" },
				"south": { "texture": "#main", "tintindex": 0, "cullface": "south" },
				"west": { "texture": "#main", "tintindex": 0, "cullface": "west" },
				"east": { "texture": "#main", "tintindex": 0, "cullface": "east" }
			}
		}
	]
}
